vistautils/__init__.py
vistautils/_graph.py
vistautils/annotated_text_utils.py
vistautils/attrutils.py
vistautils/checkpoints.py
vistautils/class_utils.py
vistautils/collection_utils.py
vistautils/io_utils.py
vistautils/iter_utils.py
vistautils/iterutils.py
vistautils/key_value.py
vistautils/logging_utils.py
vistautils/memory_amount.py
vistautils/misc_utils.py
vistautils/parameters.py
vistautils/parameters_only_entrypoint.py
vistautils/preconditions.py
vistautils/py.typed
vistautils/range.py
vistautils/span.py
vistautils/version.py
vistautils/scripts/__init__.py
vistautils/scripts/directory_to_key_value_store.py
vistautils/scripts/downsample_key_value_store.py
vistautils/scripts/join_key_value_stores.py
vistautils/scripts/split_key_value_store.py
vistautils/scripts/tar_gz_to_zip.py
vistautils/scripts/text_at_offsets.py
vistautils-0.24.0.data/scripts/downsample_key_value_store.py
vistautils-0.24.0.data/scripts/join_key_value_stores.py
vistautils-0.24.0.data/scripts/split_key_value_store.py
vistautils-0.24.0.data/scripts/tar_gz_to_zip.py
vistautils-0.24.0.dist-info/LICENSE
vistautils-0.24.0.dist-info/METADATA
vistautils-0.24.0.dist-info/WHEEL
vistautils-0.24.0.dist-info/top_level.txt
vistautils-0.24.0.dist-info/RECORD
