Metadata-Version: 2.1
Name: vistautils
Version: 0.24.0
Summary: Python utilities developed by USC ISI's VISTA center
Home-page: https://github.com/isi-vista/vistautils
Author: Ryan Gabbard <gabbard@isi.edu> and Constantine Lignos <lignos@isi.edu>
Author-email: gabbard@isi.edu
License: UNKNOWN
Platform: UNKNOWN
Classifier: Programming Language :: Python :: 3
Classifier: License :: OSI Approved :: MIT License
Classifier: Operating System :: OS Independent
Requires-Python: ~=3.6
Requires-Dist: immutablecollections (>=0.9.0)
Requires-Dist: attrs (>=19.2.0)
Requires-Dist: pyyaml (>=5.1)
Requires-Dist: typing-extensions
Requires-Dist: sortedcontainers (>=2.1.0)
Requires-Dist: deprecation (>=2.1.0)
